{
  "dataset_id": "ds004022",
  "num_citations": 2,
  "date_last_updated": "2025-07-26T18:48:08.755511+00:00",
  "metadata": {
    "total_cumulative_citations": 4,
    "fetch_date": "2025-07-26T18:48:08.755511+00:00",
    "processing_version": "1.0"
  },
  "citation_details": [
    {
      "title": "FBLPF-ABOW: an effective method for blink artifact removal in single-channel EEG signal",
      "author": "W Gao, D Liu, Q Wang, Y Zhao",
      "venue": "IEEE Journal of Biomedical and Health Informatics",
      "year": 2023,
      "url": "https://ieeexplore.ieee.org/abstract/document/10246981/",
      "cited_by": 4,
      "abstract": "Objective: The latest development in low-cost single-channel Electroencephalography (EEG)  devices is gaining widespread attention because it reduces hardware complexity. Discrete",
      "short_author": "W Gao, D Liu, Q Wang, Y Zhao",
      "publisher": "IEEE",
      "pages": "5722--5733",
      "volume": "27",
      "journal": "IEEE Journal of Biomedical and Health Informatics",
      "pub_type": "article",
      "bib_id": "gao2023fblpf"
    },
    {
      "title": "Adversarial denoising of EEG signals: a comparative analysis of standard GAN and WGAN-GP approaches",
      "author": "IE Tibermacine, S Russo, F Citeroni",
      "venue": "Frontiers in Human Neuroscience",
      "year": 2025,
      "url": "https://www.frontiersin.org/journals/human-neuroscience/articles/10.3389/fnhum.2025.1583342/full",
      "cited_by": 0,
      "abstract": "Introduction Electroencephalography (EEG) signals frequently contain substantial noise and  interference, which can obscure clinically and scientifically relevant features. Traditional",
      "short_author": "IE Tibermacine, S Russo, F Citeroni",
      "publisher": "Frontiers Media SA",
      "pages": "1583342",
      "volume": "19",
      "journal": "Frontiers in Human Neuroscience",
      "pub_type": "article",
      "bib_id": "tibermacine2025adversarial"
    }
  ]
}