{
  "dataset_id": "ds004517",
  "num_citations": 3,
  "date_last_updated": "2025-07-26T18:48:08.715015+00:00",
  "metadata": {
    "total_cumulative_citations": 3,
    "fetch_date": "2025-07-26T18:48:08.715015+00:00",
    "processing_version": "1.0"
  },
  "citation_details": [
    {
      "title": "Banding survey at colonies of brent goose, Branta bernicla in the Lena Delta, Russia, and a recovery record",
      "author": "Y Sawa, T Sato, T Ikeuchi",
      "venue": "The Bulletin of the Japanese Bird Banding Association",
      "year": 2019,
      "url": "https://scholar.archive.org/work/ps3aklzilffptcbnppakwbatae/access/wayback/https://www.jstage.jst.go.jp/article/jbba/31/1_2/31_MS117/_pdf",
      "cited_by": 3,
      "abstract": "A banding expedition for Brent Geese Branta bernicla was conducted in the northeast of the  Lena Delta, Russian Federation in July 2016. A total of 63 Brent Goose nests were found on",
      "short_author": "Y Sawa, T Sato, T Ikeuchi",
      "pages": "53--64",
      "volume": "31",
      "journal": "The Bulletin of the Japanese Bird Banding Association",
      "pub_type": "article",
      "bib_id": "sawa2019banding"
    },
    {
      "title": "Simultaneous EEG and fNIRS recordings for semantic decoding of imagined animals and tools",
      "author": "M Rybář, R Poli, I Daly",
      "venue": "Scientific Data",
      "year": 2025,
      "url": "https://www.nature.com/articles/s41597-025-04967-0",
      "cited_by": 0,
      "abstract": "Semantic neural decoding aims to identify which semantic concepts an individual focuses on  at a given moment based on recordings of their brain activity. We investigated the feasibility",
      "short_author": "M Rybář, R Poli, I Daly"
    },
    {
      "title": "ロシア・レナデルタのコロニーにおけるコクガンの標識調査および回収記録",
      "author": "澤祐介， 佐藤達夫， 池内俊雄",
      "venue": "日本鳥類標識協会誌",
      "year": 2019,
      "url": "https://www.jstage.jst.go.jp/article/jbba/31/1_2/31_MS117/_article/-char/ja/",
      "cited_by": 0,
      "abstract": "Banding survey at colonies of Brent Goose, Branta bernicla in the Lena Delta, Russia and a  recovery record Page 1 Introduction A subspecies of Brent Goose, Branta bernicla nigricans,",
      "short_author": "澤祐介， 佐藤達夫， 池内俊雄"
    }
  ]
}