{
  "dataset_id": "ds003810",
  "num_citations": 2,
  "date_last_updated": "2025-07-26T18:48:08.888342+00:00",
  "metadata": {
    "total_cumulative_citations": 4,
    "fetch_date": "2025-07-26T18:48:08.888342+00:00",
    "processing_version": "1.0"
  },
  "citation_details": [
    {
      "title": "Multivariate Fast Iterative Filtering Based Automated System for Grasp Motor Imagery Identification Using EEG Signals",
      "author": "S Sharma, A Shedsale, RR Sharma",
      "venue": "International Journal of Human--Computer Interaction",
      "year": 2023,
      "url": "https://www.tandfonline.com/doi/abs/10.1080/10447318.2023.2280327",
      "cited_by": 0,
      "abstract": "One of the most crucial use of hands in daily life is grasping. Sometimes people with  neuromuscular disorders become incapable of moving their hands. This article proposes a grasp",
      "short_author": "S Sharma, A Shedsale, RR Sharma",
      "publisher": "Taylor \\& Francis",
      "pages": "1--9",
      "journal": "International Journal of Human--Computer Interaction",
      "pub_type": "article",
      "bib_id": "sharma2023multivariate"
    },
    {
      "title": "A motor imagery vs. rest dataset with low-cost consumer grade EEG hardware",
      "author": "V Peterson, C Galván, H Hernández, MP Saavedra",
      "venue": "Data in Brief",
      "year": 2022,
      "url": "https://www.sciencedirect.com/science/article/pii/S2352340922004280",
      "cited_by": 4,
      "abstract": "The data consist of electroencephalography (EEG) signals acquired by means of low-cost  consumer-grade devices from 10 participants (four females, right-handed, mean age ± SD =",
      "short_author": "V Peterson, C Galván, H Hernández, MP Saavedra"
    }
  ]
}