{
  "dataset_id": "ds004502",
  "num_citations": 3,
  "date_last_updated": "2025-07-24T22:17:25.859080+00:00",
  "metadata": {
    "total_cumulative_citations": 5,
    "fetch_date": "2025-07-24T22:17:25.859080+00:00",
    "processing_version": "1.0"
  },
  "citation_details": [
    {
      "title": "Banding survey at colonies of Brent Goose, Branta bernicla in the Lena Delta, Russia, and a recovery record",
      "author": "Y Sawa, T Sato, T Ikeuchi",
      "venue": "Bull Jpn Bird Banding Assoc",
      "year": 2019,
      "url": "https://scholar.archive.org/work/ps3aklzilffptcbnppakwbatae/access/wayback/https://www.jstage.jst.go.jp/article/jbba/31/1_2/31_MS117/_pdf",
      "cited_by": 2,
      "abstract": "A banding expedition for Brent Geese Branta bernicla was conducted in the northeast of the  Lena Delta, Russian Federation in July 2016. A total of 63 Brent Goose nests were found on",
      "short_author": "Y Sawa, T Sato, T Ikeuchi",
      "pages": "53--64",
      "volume": "31",
      "journal": "Bull Jpn Bird Banding Assoc",
      "pub_type": "article",
      "bib_id": "sawa2019banding"
    },
    {
      "title": "Preparatory neural activity differs between selective attention and perceptual expectations",
      "author": "JMG Peñalver, D López-García, C González-García",
      "venue": "bioRxiv",
      "year": 2022,
      "url": "https://www.biorxiv.org/content/10.1101/2022.09.13.507583.abstract",
      "cited_by": 3,
      "abstract": "Proactive cognition brain models are mainstream nowadays. Within these, preparation is  understood as an endogenous, top-down function that takes place prior to the actual",
      "short_author": "JMG Peñalver, D López-García, C González-García"
    },
    {
      "title": "ロシア・レナデルタのコロニーにおけるコクガンの標識調査および回収記録",
      "author": "澤祐介， 佐藤達夫， 池内俊雄",
      "venue": "日本鳥類標識協会誌",
      "year": 2019,
      "url": "https://www.jstage.jst.go.jp/article/jbba/31/1_2/31_MS117/_article/-char/ja/",
      "cited_by": 0,
      "abstract": "Banding survey at colonies of Brent Goose, Branta bernicla in the Lena Delta, Russia and a  recovery record Page 1 Introduction A subspecies of Brent Goose, Branta bernicla nigricans,",
      "short_author": "澤祐介， 佐藤達夫， 池内俊雄"
    }
  ]
}