{
  "dataset_id": "ds002725",
  "date_retrieved": "2025-07-31T00:19:15.881804+00:00",
  "dataset_description": {
    "Name": "A dataset recording joint EEG-fMRI during affective music listening ",
    "BIDSVersion": "1.0.2",
    "Authors": [
      "Ian Daly",
      "Nicoletta Nicolaou",
      "Duncan Williams",
      "Faustina Hwang",
      "Alexis Kirke",
      "Eduardo Miranda",
      "Slawomir J. Nasuto"
    ],
    "License": "CC0",
    "DatasetDOI": "10.18112/openneuro.ds002725.v1.0.0"
  },
  "readme_content": "Dataset: Joint EEG-fMRI recording during affective music listening.\r\n\r\nThis dataset was recorded from 21 healthy adult participants viia a joint EEG-fMRI modality while they\r\nlistened to a set of music stimuli chosen and generated to produce different affective (emotional)\r\nreponses. Participants self-reported their felt affective states as they listened to the music.\r\n\r\nThe full experiment description can be found in our paper (Daly et.al., 2019).\r\n\r\nData recorded in 2016\r\n\r\nPublished in 2019\r\n\r\n[1] Daly, I., Williams, D., Hwang, F., Kirke, A., Miranda, E. R., & Nasuto, S. J. (2019). Electroencephalography reflects the activity of sub-cortical brain regions during approach-withdrawal behaviour while listening to music. Scientific Reports, 9(1), 9415. https://doi.org/10.1038/s41598-019-45105-2\r\n\r\n",
  "github_info": {
    "repository_url": "https://github.com/OpenNeuroDatasets/ds002725",
    "exists": true,
    "description": null,
    "created_at": "2020-04-24T19:31:28+00:00",
    "updated_at": "2020-04-24T19:34:18+00:00",
    "default_branch": "master"
  },
  "retrieval_status": {
    "dataset_description": "not_found",
    "readme": "not_found",
    "repository": "success"
  }
}